innopy/__init__.py
innopy/innogy_device.py
innopy/innogy_event.py
innopy/innopy_client.py
innopy/innopy_constants.py
innopy/innopy_device_types.py
innopy/util.py
innopy-0.1.7.dist-info/LICENSE
innopy-0.1.7.dist-info/METADATA
innopy-0.1.7.dist-info/WHEEL
innopy-0.1.7.dist-info/top_level.txt
innopy-0.1.7.dist-info/RECORD
