Metadata-Version: 2.1
Name: innopy
Version: 0.1.7
Summary: API for communicating with Livisi/Innogy Smarthome
Home-page: https://github.com/muhmuhkuh/innopy
Author: Example Author
Author-email: author@example.com
License: UNKNOWN
Project-URL: Bug Tracker, https://github.com/muhmuhkuh/innopy/issues
Platform: UNKNOWN
Classifier: Programming Language :: Python :: 3
Classifier: License :: OSI Approved :: MIT License
Classifier: Operating System :: OS Independent
Requires-Python: >=3.6
License-File: LICENSE
Requires-Dist: sanction
Requires-Dist: aiohttp
Requires-Dist: requests
Requires-Dist: requests-oauthlib
Requires-Dist: ratelimit
Requires-Dist: websockets
Requires-Dist: colorlog
